Workbook

Sheet Dashboard
A1: THE FIRST EDIT
A2: Budget & stock tracker | Starting capital: KSh 5,000
A4: Starting budget (KSh) | B4: 5000
A5: Total expenses recorded (KSh) | B5: =SUM(Expenses!D2:D101)
A6: Remaining budget (KSh) | B6: =B4-B5
A7: Pieces recorded | B7: =COUNTA(Inventory!B2:B101)
A8: Pieces sold | B8: =COUNTIF(Inventory!H2:H101,"Sold")
A9: Sales revenue (KSh) | B9: =SUM(Inventory!I2:I101)
A10: Estimated profit on sold pieces (KSh) | B10: =SUM(Inventory!J2:J101)
A12: How to use
A13: 1. Add every business cost to the Expenses sheet.
A14: 2. Add each clothing item to Inventory; use a unique item code.
A15: 3. Enter a sale price only when the item sells; set status to Sold.
A16: 4. The remaining budget is calculated from all expenses entered.
A17: 5. Keep personal spending separate from business spending.

Sheet Expenses
A1: Date | B1: Category | C1: Description | D1: Amount (KSh) | E1: Payment method | F1: Notes

Sheet Inventory
A1: Item code | B1: Item / description | C1: Size / measurements | D1: Condition / notes | E1: Item cost (KSh) | F1: Extra costs (KSh) | G1: Planned price (KSh) | H1: Status | I1: Sale revenue (KSh) | J1: Profit (KSh) | K1: Date sourced | L1: Date sold
J2: =IF(I2="","",I2-E2-F2)
J3: =IF(I3="","",I3-E3-F3)
J4: =IF(I4="","",I4-E4-F4)
J5: =IF(I5="","",I5-E5-F5)
J6: =IF(I6="","",I6-E6-F6)
J7: =IF(I7="","",I7-E7-F7)
J8: =IF(I8="","",I8-E8-F8)
J9: =IF(I9="","",I9-E9-F9)
J10: =IF(I10="","",I10-E10-F10)
J11: =IF(I11="","",I11-E11-F11)
J12: =IF(I12="","",I12-E12-F12)
J13: =IF(I13="","",I13-E13-F13)
... J101: =IF(I101="","",I101-E101-F101)

Sheet Content Planner
A1: Date | B1: Platform | C1: Theme | D1: Hook / idea | E1: What to film (faceless) | F1: Caption | G1: Status | H1: Post link / notes
